ScreenAmbience/__init__.py
ScreenAmbience/colors.py
ScreenAmbience/message.py
ScreenAmbience/ratios.py
ScreenAmbience/strip.py
ScreenAmbience-1.0.6.dist-info/METADATA
ScreenAmbience-1.0.6.dist-info/RECORD
ScreenAmbience-1.0.6.dist-info/WHEEL
ScreenAmbience-1.0.6.dist-info/top_level.txt
